anomaly_detection-1.0.0.dist-info/DESCRIPTION.rst
anomaly_detection-1.0.0.dist-info/METADATA
anomaly_detection-1.0.0.dist-info/RECORD
anomaly_detection-1.0.0.dist-info/WHEEL
anomaly_detection-1.0.0.dist-info/metadata.json
anomaly_detection-1.0.0.dist-info/top_level.txt
anoms/__init__.py
anoms/holt_winters.py
