Metadata-Version: 2.0
Name: anomaly-detection
Version: 1.0.0
Summary: An Anomaly Detection Package
Home-page: https://github.com/GYXie/anomaly-detection
Author: Guiyang Xie
Author-email: keen.guiyang.xie@gmail.com
License: UNKNOWN
Keywords: anomaly holt-winters
Platform: UNKNOWN
Classifier: Development Status :: 3 - Alpha
Classifier: Intended Audience :: Developers
Classifier: Topic :: Software Development :: Build Tools
Classifier: License :: OSI Approved :: MIT License
Classifier: Programming Language :: Python :: 2
Classifier: Programming Language :: Python :: 2.7
Classifier: Programming Language :: Python :: 3
Classifier: Programming Language :: Python :: 3.4
Classifier: Programming Language :: Python :: 3.5
Classifier: Programming Language :: Python :: 3.6
Requires-Dist: scipy
